{
  "game.action.block": "阻挡",
  "game.action.foul": "犯规",
  "game.action.hurlTeammate": "投掷队友",
  "game.action.mark": "盯防",
  "game.action.pass": "传球",
  "game.action.reserves": "上场",
  "game.action.run": "奔跑",
  "game.action.sidestep": "侧步",
  "game.action.stand_up": "起身",
  "game.announcement.cleanSweep": "一网打尽！",
  "game.announcement.enteredEndgame": "残局模式",
  "game.announcement.gameEndedClock": "%{coachName}赢得比赛（高分胜利）!",
  "game.announcement.gameEndedForfeit": "%{coachName}赢得比赛（对方弃赛）!",
  "game.announcement.gameEndedSuddenDeath": "%{coachName}赢得比赛（突然死亡胜利）!",
  "game.announcement.gameEndedTie": "平局!",
  "game.announcement.randomEvent": "随机事件: %{bonusPlay}!",
  "game.announcement.touchDown": "%{playerNumber}达阵 !",
  "game.armourRollModification.absoluteCarnageBonusPlay": "对方教练使用 '%{bonusPlay}'",
  "game.armourRollModification.crumblingPitch": "球场各种碎石",
  "game.armourRollModification.hurledPlayerWasAccurate": "球员被砸倒",
  "game.armourRollModification.kerrunch": "此次阻挡行动的结果是 %{result}",
  "game.blockDieResultDescription.kerrunch": "阻挡目标被击倒。此外，在对阻挡目标做护甲检定时，此次掷骰结果-1。",
  "game.blockDieResultDescription.miss": "阻挡目标不受影响。此外，执行此次阻挡行动的球员在本回合中不能再执行任何行动（包括额外行动）。",
  "game.blockDieResultDescription.shove": "阻挡目标被推离一格，然后执行此次阻挡行动的球员可以选择是否跟进，并移动到阻挡目标被推离前所占据的方格。如果阻挡目标因被推离而进入到被占据的方格或障碍物方格、或者使阻挡目标离开球场，则阻挡目标被击倒。",
  "game.blockDieResultDescription.smash": "阻挡目标被击倒。被击倒的球员变为倒地状态并被放置在其所在格倒地。如果该球员拿住球，则球在其所在格弹跳。然后，阻挡目标所属教练必须对其做护甲检定。",
  "game.blockDieResultDescription.tackle": "阻挡目标被击倒。此外，执行此次阻挡行动的球员在本回合中不能再执行任何行动（包括额外行动）。",
  "game.blockDieResultName.kerrunch": "超级猛撞！",
  "game.blockDieResultName.miss": "失误",
  "game.blockDieResultName.shove": "推离",
  "game.blockDieResultName.smash": "猛撞！",
  "game.blockDieResultName.tackle": "擒抱",
  "game.blockRollModification.playerHasSkill": "该球员拥有 '%{skill}'",
  "game.blockRollModification.playerUsedSkill": "该球员使用 '%{skill}'",
  "game.blockRollModification.targetHasSkill": "该目标球员拥有 '%{skill}'",
  "game.blockRollModification.targetUsedBonusPlay": "该目标球员使用 '%{bonusPlay}'",
  "game.board.s1b1": "白狼沙场",
  "game.board.s1b2": "阿尔特多夫废墟",
  "game.board.s2b1": "巴拉克·瓦尔斗技场",
  "game.board.s2b2": "格伦德球场",
  "game.board.s3b1": "欧甘岩地",
  "game.board.s3b2": "比尔巴利港湾",
  "game.board.s4b1": "NAF体育场",
  "game.board.s4b2": "内赫哈拉墓场",
  "game.bonusPlayDescription.absoluteCarnage": "在对方教练做护甲检定前，发动这张卡。此次护甲检定在应用其他任何修正的基础上、掷骰结果-2（此次护甲检定结果的最小值为1）。",
  "game.bonusPlayDescription.absolutelyNails": "在你球队中的一名球员做护甲检定前，发动这张卡。在那次护甲检定中，掷出的点数为2或以上（无修正）总是成功。",
  "game.bonusPlayDescription.accuratePass": "在你球队中的一名球员执行一次传球行动（此次传球行动为短距离传球）前，发动这张卡。在那次传球行动中，把执行传球行动的球员的传球值视为2+。",
  "game.bonusPlayDescription.assistedPlay": "在你的回合开始时、在“回合前流程”前，发动这张卡。在这个回合中，你球队中的球员执行的阻挡行动均视为有协助。",
  "game.bonusPlayDescription.bananaSkins": "每名教练选择一名站立（但未被盯防）的对方球员（如果有的话）。被选中的球员变为倒地状态（不做护甲检定）。如果它们拿住球，则球弹跳。",
  "game.bonusPlayDescription.bladedKnuckleDusters3E": "在你球队的一名球员执行完一次阻挡行动导致一名对方球员被击倒后，发动这张卡。那名对方球员受伤、并放置在球员席--不要做护甲检定。",
  "game.bonusPlayDescription.bladedKnuckleDusters4E": "在你球队的一名球员执行完一次阻挡行动导致一名对方球员被击倒后，发动这张卡。在此次护甲检定中，该对方球员的护甲值为6+。",
  "game.bonusPlayDescription.blitz": "在你球队中的一名球员执行完一次盯防行动、且在这个回合中已经执行过一次奔跑行动后，发动这张卡。该球员立即执行一次额外的阻挡行动、阻挡目标是被该球员盯防的一名对方球员。",
  "game.bonusPlayDescription.bodyCheck": "在你球队中的一名球员执行一次阻挡行动后、但在你掷阻挡骰前，发动这张卡--不要掷此次阻挡骰，那次阻挡行动的阻挡结果为“超级猛撞！”。",
  "game.bonusPlayDescription.bribedRef": "立即发动这张卡--不要把这张卡加入到你的手卡。在这场比赛的剩余时间里，对方教练在“回合前流程”的“紧急上场步骤”期间不能执行额外的上场行动。",
  "game.bonusPlayDescription.comboPlay": "在你球队中的一名球员因一次传球行动而拿住球后、在“获得挑战卡步骤”前，发动这张卡。该球员可以立即执行一次额外的奔跑行动（如果处于无人盯防状态）、或执行一次额外的侧步行动（如果处于被盯防状态）。",
  "game.bonusPlayDescription.crumblingPitch": "在比赛的剩余时间里，当任何球员因阻挡行动而做护甲检定时，该护甲检定应用一个-1修正。",
  "game.bonusPlayDescription.distraction": "在一名对方球员执行完一次盯防行动后、在“获得挑战卡步骤”前，发动这张卡。从你的球队中选择一名与那名对方球员相邻的球员。该球员可以执行一次额外的侧步行动。",
  "game.bonusPlayDescription.divingTackle": "在你球队中的一名球员执行完一次盯防行动后，发动这张卡。该球员可以执行一次额外的阻挡行动。在执行完此次阻挡行动后，你的球员（该球员）变为倒地状态但不为它做护甲检定。如果那名球员拿住球，则那个球弹跳。",
  "game.bonusPlayDescription.dodge": "在你球队的一名球员执行一次奔跑行动前，发动这张卡。只在那次奔跑行动中，可以移动到与对方球员相邻的方格，但在执行完此次奔跑行动后，它必须处于无人盯防状态。",
  "game.bonusPlayDescription.emptyTheBench": "所有场下球员都可以执行一次额外的上场行动。",
  "game.bonusPlayDescription.generousCoaches": "在比赛的剩余时间里，每当有球队获得一张挑战卡后、或者完成一次达阵得分后，该球队额外得1分。",
  "game.bonusPlayDescription.getInThere": "在你球队的一名球员因受伤而被放置在球员席后，发动这张卡。那名球员立即执行一次额外的上场行动。",
  "game.bonusPlayDescription.getTheRef": "在比赛的剩余时间里，每当球员执行犯规行动时，把犯规结果的“被发现了！”视为“踩偏了！”、把“接招！”视为“下去吧！”。",
  "game.bonusPlayDescription.hailMaryPass": "当你球队中的一名球员在执行一次传球行动（不包括投掷队友行动）时，发动这张卡。可以选择在球场上任何地方的、你球队中的一名球员作为此次传球目标，且此次传球检定，只要掷骰结果为4或以上，则总是成功。此次传球检定无任何修正。掷出的点数为1（在修正前或修正后）会导致脱手。",
  "game.bonusPlayDescription.impatientCoaches": "丢弃所有活跃挑战卡。之后从挑战卡卡组顶部抽出三张挑战卡并放置到活跃挑战卡区。",
  "game.bonusPlayDescription.inspiration": "在你的第三次球员行动（球员行动3）的“获得挑战卡步骤”后，发动这张卡。立即执行第四次球员行动。这次行动仍然算作你回合的一部分、且遵循所有与行动和获得挑战卡相关的规则。",
  "game.bonusPlayDescription.intervention": "在一名对方球员执行完一次盯防行动后、发动这张卡并中断。从你的球队中选择一名无人盯防球员。那名球员可以执行一次额外的盯防行动，但在执行完那次行动后，必须移动到与那名执行奔跑行动的对方球员相邻的方格。",
  "game.bonusPlayDescription.jumpUp3E": "在“回合前流程”后，但在你执行第一次球员行动前，发动这张卡。选择你球队的一名倒地球员--那名球员执行一次额外的起身行动。",
  "game.bonusPlayDescription.jumpUp4E": "选择你球队的一名倒地球员。该球员可以执行一次额外的起身行动。",
  "game.bonusPlayDescription.legUp": "在你的球队获得一张挑战卡后、或者完成一次达阵得分后，发动这张卡。你的球队得1分。",
  "game.bonusPlayDescription.longMark": "在你球队中的一名球员执行一次盯防行动前，发动这张卡。只在那次盯防行动中，该球员最多可以移动4格而不是2格。",
  "game.bonusPlayDescription.multiBall3E": "立即发动这张卡--不要把这张卡加入到你的手卡。两个新的橄榄球进入球场。",
  "game.bonusPlayDescription.multiBall4E": "如果球场有球，则一个新的橄榄球进入球场。如果球场没球，则两个新的橄榄球进入球场。",
  "game.bonusPlayDescription.nervesOfSteel": "在执行一次球员行动前，发动这张卡。仅在此次行动中，你球队的一名球员，即使它处于被盯防状态，也可以执行传球行动（包括投掷队友行动）。",
  "game.bonusPlayDescription.nufflesBlessing": "立即发动这张卡--不要把这张卡加入到你的手卡。你球队中的球员执行的阻挡行动均视为有协助。这张卡的效果将持续到比赛结束。",
  "game.bonusPlayDescription.passingPlay": "在“回合前流程”后，发动这张卡。在这个回合期间，当你的一名球员做传球检定时，掷一枚D8而不是D6。掷出的点数为6或以上（在修正前或修正后）总是成功。",
  "game.bonusPlayDescription.pitchInvasion": "每名教练为对方球队的每名站立球员、被盯防球员或倒地球员掷一枚阻挡骰。如果一名对方球员的掷骰结果为“超级猛撞！”，则该球员受伤并被放置在其所属球队的球员席。如果该球员拿着球，则球弹跳。其他任何掷骰结果均没有效果。",
  "game.bonusPlayDescription.pro": "在你球队中的一名球员做传球检定或护甲检定前，发动这张卡。在那次检定中掷一枚D8而不是D6。掷出的点数为6或以上（在修正前或修正后）总是成功。",
  "game.bonusPlayDescription.rawTalent": "在你做传球检定、做护甲检定、或你球队的一名球员因执行一次阻挡行动而掷阻挡骰后，发动这张卡。重掷那次掷骰。",
  "game.bonusPlayDescription.readyToGo": "立即发动这张卡--不要把这张卡加入到你的手卡。你球队中的每一名无人盯防球员可以执行一次额外的、移动一格的奔跑行动。那之后，你球队中的每一名被盯防球员可以执行一次额外的侧步行动。那之后，你球队中的每一名倒地球员可以执行一次额外的起身行动。",
  "game.bonusPlayDescription.reserves3E": "在“回合前流程”后，但在你执行第一次球员行动前，发动这张卡。执行一次额外的上场行动。",
  "game.bonusPlayDescription.reserves4E": "在你执行一次球员行动前，发动这张卡。你球员席的一名球员可以执行一次额外的上场行动。",
  "game.bonusPlayDescription.reset": "从当前回合的教练开始，双方教练把球场上和球员席所有球员都移除，并按照“设置游戏”规则把它们放置到端区。比赛由此事件发生时轮到的教练继续进行。",
  "game.bonusPlayDescription.rushingPlay": "在你回合的“回合前流程”后，但在你执行第一次球员行动前，发动这张卡。在这个回合中，你球队中的球员在执行奔跑行动时，可以移动到与对方球员相邻的方格，但这样做会结束此次奔跑行动。",
  "game.bonusPlayDescription.shadow": "在一名对方球员执行完一次侧步行动后，发动这张卡并中断。从你的球队中选择一名球员（被选中的球员得在那次侧步行动前就盯防那名对方球员）。该球员移动到那名对方球员腾出的方格。",
  "game.bonusPlayDescription.shoulderCharge": "在你球队中的一名球员执行一次盯防行动后，发动这张卡。那名球员立即执行一次阻挡行动、阻挡目标为被该球员盯防的一名对方球员。",
  "game.bonusPlayDescription.sprint": "在你球队的一名球员执行一次奔跑行动前，发动这张卡。在那次奔跑行动中，那名球员的移动值+2。",
  "game.bonusPlayDescription.stepAside3E": "在你球队中的一名球员被选为一次阻挡行动的目标后、但在掷此次阻挡骰前，发动这张卡。那名球员可以立即执行一次额外的侧步行动（在此之后该球员必须处于无人盯防状态，而不是被盯防状态）。此外，此次阻挡行动被取消，且此次阻挡行动不算作已经执行过。",
  "game.bonusPlayDescription.stepAside4E": "在一名对方球员执行完一次盯防行动后，发动这张卡并中断。从你的球队中选择一名被那名对方球员盯防的球员。该球员可以执行一次额外的侧步行动。",
  "game.bonusPlayDescription.theKidsGotMoxy": "当你球队中的一名球员在执行一次无协助的阻挡行动时，发动这张卡。在那次阻挡行动中掷三枚阻挡骰。",
  "game.bonusPlayDescription.toughEnough3E": "在你球队中的一名球员做护甲检定前，发动这张卡。在那次检定中掷一枚D8而不是D6。掷出的点数为6或以上（在修正前或修正后）总是成功。",
  "game.bonusPlayDescription.toughEnough4E": "在你球队中的一名球员被选为阻挡行动的目标、在掷阻挡骰前，发动这张卡并中断。此次对方球员的阻挡行动不能获得协助，并把阻挡结果的“推离”视为“失误”。",
  "game.bonusPlayDescription.trapdoorMonster": "随机选择一个活板门。站在该活板门上的任何球员会受伤。每名与该活板门相邻的站立球员或被盯防球员都变为倒地状态（不做护甲检定）。如果这些球员中有任何球员拿住球，则球弹跳。",
  "game.bonusPlayDescription.yourTimeToShine": "立即发动这张卡--不要把这张卡加入到你的手卡。执行两次额外的上场行动。那之后，其中一名因此效果而执行过上场行动的球员，在这个回合中可以执行一次额外的奔跑行动。",
  "game.bonusPlayName.absoluteCarnage": "锈蚀诅咒",
  "game.bonusPlayName.absolutelyNails": "绝对防御",
  "game.bonusPlayName.accuratePass": "精准传球",
  "game.bonusPlayName.assistedPlay3E": "协防战术",
  "game.bonusPlayName.assistedPlay4E": "阻挡战术",
  "game.bonusPlayName.bananaSkins": "香蕉皮",
  "game.bonusPlayName.bladedKnuckleDusters": "锋利指虎",
  "game.bonusPlayName.blitz": "突袭！",
  "game.bonusPlayName.bodyCheck": "以身阻挡",
  "game.bonusPlayName.bribedRef": "贿赂裁判",
  "game.bonusPlayName.comboPlay": "连环战术",
  "game.bonusPlayName.crumblingPitch": "碎石球场",
  "game.bonusPlayName.distraction": "分散注意力",
  "game.bonusPlayName.divingTackle": "鱼跃擒抱",
  "game.bonusPlayName.dodge": "闪避",
  "game.bonusPlayName.emptyTheBench": "板凳清空",
  "game.bonusPlayName.generousCoaches": "慷慨的教练",
  "game.bonusPlayName.getInThere": "马上回场！",
  "game.bonusPlayName.getTheRef": "搞定裁判！",
  "game.bonusPlayName.hailMaryPass": "万福玛利亚传球",
  "game.bonusPlayName.impatientCoaches": "急躁的教练",
  "game.bonusPlayName.inspiration": "灵感",
  "game.bonusPlayName.intervention": "妨碍",
  "game.bonusPlayName.jumpUp": "快速起身",
  "game.bonusPlayName.legUp": "起势",
  "game.bonusPlayName.longMark3E": "干扰",
  "game.bonusPlayName.longMark4E": "侵略性盯防",
  "game.bonusPlayName.multiBall": "多个橄榄球",
  "game.bonusPlayName.nervesOfSteel": "钢铁意志",
  "game.bonusPlayName.nufflesBlessing": "纳弗尔神的眷顾",
  "game.bonusPlayName.passingPlay": "传球战术",
  "game.bonusPlayName.pitchInvasion": "球场入侵",
  "game.bonusPlayName.pro": "专业",
  "game.bonusPlayName.rawTalent": "天赋",
  "game.bonusPlayName.readyToGo": "准备好了",
  "game.bonusPlayName.reserves": "上场",
  "game.bonusPlayName.reset": "重置！",
  "game.bonusPlayName.rushingPlay3E": "阻挡战术",
  "game.bonusPlayName.rushingPlay4E": "协防战术",
  "game.bonusPlayName.shadow3E": "影随",
  "game.bonusPlayName.shadow4E": "影随",
  "game.bonusPlayName.shoulderCharge": "肩膀撞击",
  "game.bonusPlayName.sprint": "冲刺",
  "game.bonusPlayName.stepAside": "摆脱",
  "game.bonusPlayName.theKidsGotMoxy": "这小子挺身而出",
  "game.bonusPlayName.toughEnough": "足够坚韧",
  "game.bonusPlayName.trapdoorMonster": "活板门怪物",
  "game.bonusPlayName.yourTimeToShine": "你的闪耀时刻！",
  "game.challengeDeck.challengeCardClosed": "'%{challenge}'",
  "game.challengeDeck.challengeCardOpen": "'%{challenge}' (附赠战术是： '%{bonusPlay}')",
  "game.challengeDeck.descriptionMore": "挑战卡卡组还剩下%{count}挑战卡。",
  "game.challengeDeck.descriptionOne": "挑战卡卡组还剩下1张挑战卡。",
  "game.challengeDeck.descriptionZero": "挑战卡卡组已空。",
  "game.challengeDeck.title": "挑战卡卡组",
  "game.challengeDeckConfig.randomizedLong3E": "随机附赠战术的挑战卡卡组（带残局挑战卡）",
  "game.challengeDeckConfig.randomizedLong4E": "随机附赠战术的挑战卡卡组（带随机事件卡）",
  "game.challengeDeckConfig.randomizedShort3E": "随机附赠战术的挑战卡卡组（不带残局挑战卡）",
  "game.challengeDeckConfig.randomizedShort4E": "随机附赠战术的挑战卡卡组（不带随机事件卡）",
  "game.challengeDeckConfig.standardLong3E": "标准挑战卡卡组（带残局挑战卡）",
  "game.challengeDeckConfig.standardLong4E": "标准挑战卡卡组（带随机事件卡）",
  "game.challengeDeckConfig.standardShort3E": "标准挑战卡卡组（不带残局挑战卡）",
  "game.challengeDeckConfig.standardShort4E": "标准挑战卡卡组（不带随机事件卡）",
  "game.challengeDescription.breakSomeBones": "如果你球队的一名球员在执行完一次阻挡行动或犯规行动后、且目标受伤，则获得这张卡。",
  "game.challengeDescription.breakTheirLines": "如果你球队的一名拿住球的球员执行了一次阻挡行动、且阻挡目标被击倒，则获得这张卡。",
  "game.challengeDescription.causeSomeCarnage": "如果你球队的一名球员执行了一次阻挡行动且阻挡目标受伤、且在你的回合期间有至少一名或更多其他对方球员被击倒或者受伤，则获得这张卡。",
  "game.challengeDescription.freeUpTheBall": "如果一名对方球员拿住一个球、且在你球队的一名球员执行完一次行动后，该对方球员不再拿住那个球，则获得这张卡。",
  "game.challengeDescription.gangUp": "如果你球队的一名球员在执行完一次有协助的阻挡行动后、且阻挡目标被击倒，则获得这张卡。",
  "game.challengeDescription.getMoving": "在你的回合期间，如果你球队的一名球员执行了一次奔跑行动、且在你的回合期间，你的球队执行了三次或更多奔跑行动，则获得这张卡。",
  "game.challengeDescription.getTheBall": "如果你球队的一名球员拿住一个球、且在你的回合开始时你球队的所有球员都没有拿住那个球，则获得这张卡。",
  "game.challengeDescription.getTogether": "如果你球队的一名球员在执行完一次奔跑行动、盯防行动或侧步行动后、且该球员与两名或更多队友相邻，则获得这张卡。",
  "game.challengeDescription.goDeep": "如果你的球队中有两名或更多无人盯防球员在对方球队端区3格范围内，则获得这张卡。",
  "game.challengeDescription.lastChance": "如果你球队的一名球员在执行完一次行动后，你的球队得分落后对方球队4分或更多、且无法在此次行动后获得另一张挑战卡，则获得这张卡。",
  "game.challengeDescription.makeARiskyPass": "如果你球队的一名球员执行了一次成功的传球行动、且此次传球检定应用一个负面修正，则获得这张卡。",
  "game.challengeDescription.moveTheBall": "如果你球队的一名球员执行了一次传球行动或奔跑行动、且在那次行动期间，球沿远离你球队端区的方向移动4格或更多，且你球队的球员仍然拿住那个球，则获得这张卡。",
  "game.challengeDescription.pileOn": "在你的回合中，如果两名或更多对方球员在球员席、且你球队的一名球员在执行一次阻挡行动后导致阻挡目标被击倒，则获得这张卡。",
  "game.challengeDescription.playAsATeam": "在你的回合期间，如果你的球队中有三名或更多不同的球员执行了三次或更多不同的行动，则获得这张卡。",
  "game.challengeDescription.randomEvent": "这是一张随机事件卡, 一旦该卡在挑战卡卡组顶部出现，必须抽出该卡并应用其效果。",
  "game.challengeDescription.rookieBonus": "此卡是“值得关注的新秀”卡（其效果与'%{bonusPlay}' 附赠战术一样）, 给新手教练提供一次额外的重掷。",
  "game.challengeDescription.showboatForTheCrowd": "如果你球队的一名球员执行了一次行动、且那次行动导致你的球队达阵得分，则获得这张卡。",
  "game.challengeDescription.showNoFear": "在一次行动结束后，如果你球队的一名球员占据在活板门所在格、且有对方球员拿住球，则获得这张卡。",
  "game.challengeDescription.showOffALittle": "如果你球队的一名球员在此次行动中执行了一次成功的长距离传球、且此次传球是你球队的一名球员在你的回合期间执行的第二次或之后的成功传球（不包括手递手传球），则获得这张卡。",
  "game.challengeDescription.showSomeGrit": "如果你球队的一名球员在执行完一次行动后，你的球队得分落后对方球队4分或更多、且无法在此次行动后获得另一张挑战卡，则获得这张卡。",
  "game.challengeDescription.showThemHowItsDone": "在你的回合期间，如果你球队的一名球员在执行完一次行动后、且该球员执行的此次行动（不包括额外行动）是第三次或之后的、且与之前的行动不同，则获得这张卡。",
  "game.challengeDescription.showUsACompletion": "如果你球队的一名球员执行了一次传球行动（不包括手递手传球）、且那次传球行动是成功的，则获得这张卡。",
  "game.challengeDescription.spreadOut": "如果你球队的一名球员在执行完一次奔跑行动或侧步行动后、且你的球队中没有球员与一名或更多队友相邻，则获得这张卡。",
  "game.challengeDescription.takeThemDown": "如果你球队的一名球员在执行完一次阻挡行动后、且阻挡目标被击倒，则获得这张卡。",
  "game.challengeDescription.tieThemUp3E": "如果你球队的一名球员在执行完一次盯防行动后、且至少三名对方球员被两名或更多你球队的球员盯防，则获得这张卡。",
  "game.challengeDescription.tieThemUp4E": "如果你球队的一名球员在执行完一次盯防行动后、且执行完此次行动后盯防两名或更多对方球员（这些对方球员在被盯防前，未被你球队的其他球员盯防），则获得这张卡。",
  "game.challengeName.breakSomeBones": "打断骨头！",
  "game.challengeName.breakTheirLines": "打破它们的防线！",
  "game.challengeName.causeSomeCarnage": "屠杀盛宴！",
  "game.challengeName.freeUpTheBall": "打掉那个球！",
  "game.challengeName.gangUp": "一起上！",
  "game.challengeName.getMoving": "动起来！",
  "game.challengeName.getTheBall": "拿住那个球！",
  "game.challengeName.getTogether": "靠拢！",
  "game.challengeName.goDeep": "深入后场！",
  "game.challengeName.lastChance": "最后机会",
  "game.challengeName.makeARiskyPass": "赌博式传球！",
  "game.challengeName.moveTheBall": "持球推进！",
  "game.challengeName.pileOn": "大打出手！",
  "game.challengeName.playAsATeam": "打出团队配合！",
  "game.challengeName.randomEvent": "随机事件",
  "game.challengeName.rookieBonus": "值得关注的新秀",
  "game.challengeName.showboatForTheCrowd": "向观众炫耀！",
  "game.challengeName.showNoFear": "无所畏惧！",
  "game.challengeName.showOffALittle": "炫耀一下！",
  "game.challengeName.showSomeGrit": "拿出点勇气！",
  "game.challengeName.showThemHowItsDone": "让它们看看它如何做到的！",
  "game.challengeName.showUsACompletion": "完成连线！",
  "game.challengeName.spreadOut": "散开！",
  "game.challengeName.takeThemDown": "放倒它们！",
  "game.challengeName.tieThemUp": "盯住它们！",
  "game.direction.east": "东",
  "game.direction.north": "南",
  "game.direction.northEast": "东南",
  "game.direction.northWest": "西南",
  "game.direction.south": "北",
  "game.direction.southEast": "东北",
  "game.direction.southWest": "西北",
  "game.direction.west": "西",
  "game.foulDieResultDescription.gotThem": "犯规目标受伤。",
  "game.foulDieResultDescription.slipped": "犯规目标不受影响，但执行此次犯规行动的球员在本回合中不能再执行任何行动（包括额外行动）。",
  "game.foulDieResultDescription.spotted": "犯规目标不受影响。执行此次犯规行动的球员因被裁判发现，并驱逐出场。",
  "game.foulDieResultDescription.takeThat": "犯规目标受伤。执行此次犯规行动的球员因被裁判发现，并驱逐出场。",
  "game.foulDieResultName.gotThem": "下去吧！",
  "game.foulDieResultName.slipped": "踩偏了！",
  "game.foulDieResultName.spotted": "被发现了！",
  "game.foulDieResultName.takeThat": "接招！",
  "game.foulRollModification.getTheRef": "裁判受到干扰",
  "game.log.activatedBonusPlay": "%{coachName} 发动 '%{bonusPlay}'。",
  "game.log.activatedRandomEvent": "%{coachName} 应用一张随机事件卡: '%{bonusPlay}'。",
  "game.log.ballBounced": "球在%{source}沿%{direction}方向弹跳到%{destination}。",
  "game.log.ballCameLoose": "球落在 %{square}。",
  "game.log.ballDisappeared": "球离开球场。",
  "game.log.beganFinalTurn": "%{coachName}开始其最后一回合。",
  "game.log.beganTurn": "%{coachName}开始其回合。",
  "game.log.changedArmourResult": "护甲检定结果从%{unmodified}修正到%{modified} (%{modifications})。",
  "game.log.changedBlockResult": "阻挡结果从%{unmodified}修正到%{modified} (%{modifications})。",
  "game.log.changedDirection": "方向从%{unmodified}修正到%{modified}。",
  "game.log.changedFoulResult": "犯规结果从%{unmodified}修正到%{modified} (%{modifications})。",
  "game.log.changedHurlTeammateResult": "投掷队友检定结果从%{unmodified}修正到%{modified} (%{modifications})。",
  "game.log.changedPassResult": "传球检定结果从%{unmodified}修正到%{modified} (%{modifications})。",
  "game.log.claimedObjective": "%{coachName}获得%{ordinal}活跃挑战卡, %{objective}。",
  "game.log.dealtNewObjective": "%{coachName}刷新%{ordinal}活跃挑战卡： %{objective}。",
  "game.log.declaredFreeAction": "%{player}执行一次额外的%{action}行动。",
  "game.log.declaredPlayerAction": "%{player}执行一次%{action}行动。",
  "game.log.declinedFollowUp": "%{player}在%{action}行动后选择不跟进。",
  "game.log.declinedOffensiveSpecialistSkillReroll": "%{player}选择不使用'%{skill}'能力来重掷此次掷骰。",
  "game.log.declinedOneObjective": "%{coachName} 选择不获得'%{objective0}'.",
  "game.log.declinedSkillAction": "%{player}选择不使用'%{skill}'能力来执行%{action}行动",
  "game.log.declinedSkillActionMultiplePlayers": "%{coachName}选择不使用%{playerCount}名球员的'%{skill}'能力（满足使用条件）来执行%{action}行动。",
  "game.log.declinedThreeObjectives": "%{coachName}选择不获得'%{objective0}', '%{objective1}', 或'%{objective2}'。",
  "game.log.declinedToUseWardance": "%{player}选择不使用%{skill}来执行侧步行动。",
  "game.log.declinedTwoObjectives": "%{coachName}选择不获得'%{objective0}'和'%{objective1}'。",
  "game.log.discardedBonusPlay": "%{coachName}丢弃'%{bonusPlay}'。",
  "game.log.discardedObjective": "%{coachName}丢弃%{ordinal}活跃挑战卡,%{objective}。",
  "game.log.earnedCleanSweep": "%{coachName}因“一网打尽”而获得额外2分",
  "game.log.endedTurn": "%{coachName}结束其回合。",
  "game.log.enteredEndgame": "进入残局模式。",
  "game.log.flippedCoin": "%{coachName}赢得猜硬币。",
  "game.log.gameEndedClock": "比赛以高分结束（%{coachName}获胜！）。",
  "game.log.gameEndedForfeit": "比赛以对方弃赛结束（%{coachName}获胜！）",
  "game.log.gameEndedSuddenDeath": "比赛以突然死亡结束（%{coachName}获胜！）。",
  "game.log.gameEndedTie": "比赛以平局结束。",
  "game.log.hurledTeammateCrashedIntoGround": "%{player}因被队友投掷而碰撞着陆。",
  "game.log.hurledTeammateCrashedIntoPlayer": "%{player}因被队友投掷而砸向%{targetPlayer}。",
  "game.log.hurledTeammateLanded": "T%{player}被队友投掷后安全着陆。",
  "game.log.newBallAppeared": "一个新的橄榄球出现在%{square}。",
  "game.log.playerBlockedMoreAssists": "%{opponent}被%{player}阻挡，协助来源为%{assistsExceptLast},以及%{assistsLast}。",
  "game.log.playerBlockedOneAssist": "%{opponent}被%{player}阻挡，协助来源为%{assist}。",
  "game.log.playerBlockedTwoAssists": "%{opponent}被%{player}阻挡，协助来源为%{assist0}和%{assist1}.",
  "game.log.playerBlockedZeroAssists": "%{opponent}被%{player}阻挡。",
  "game.log.playerCannotTakeActions": "%{player}在本回合中不能再执行任何行动（包括额外行动）。",
  "game.log.playerCanTakeActions": "%{player}可以执行别的行动。",
  "game.log.playerCaughtBouncingBall": "%{player} 接住一个弹跳球。",
  "game.log.playerCaughtHandoff": "%{player}接住队友的手递手传球。",
  "game.log.playerCaughtPass": "%{player}接住队友的传球。",
  "game.log.playerFailedCatch": "%{player}接球失败。",
  "game.log.playerFellDownBananaSkin": "%{player}踩到香蕉皮后摔倒在地。",
  "game.log.playerFellDownBlocked": "%{player}因被对方阻挡后倒地。",
  "game.log.playerFellDownDivingTackle": "%{player}因一次鱼跃擒抱后倒地。",
  "game.log.playerFellDownHitByHurledPlayer": "%{player}被球员砸到后倒地。",
  "game.log.playerFellDownTrapdoorMonster": "%{player}被活板门怪物攻击后倒地。",
  "game.log.playerFouled": "%{player}被%{opponent}犯规。",
  "game.log.playerFumbledBall": "%{player}掉球。",
  "game.log.playerFumbledTeammate": "%{player}在投掷%{teammate}时脱手。",
  "game.log.playerHandedOffBall": "%{player}递球给%{direction}。",
  "game.log.playerHurledTeammate": "%{player}把%{teammate}从%{source}投掷到%{destination}.",
  "game.log.playerInjuredBlocked": "%{player}在被对方阻挡后受伤。",
  "game.log.playerInjuredBloodlust": "%{player}因“嗜血”能力而受伤。",
  "game.log.playerInjuredFouled": "%{player}因被对方犯规而受伤。",
  "game.log.playerInjuredFumbled": "%{player}因投掷队友行动脱手而受伤。",
  "game.log.playerInjuredHitByHurledPlayer": "%{player}因被球员砸倒而受伤。",
  "game.log.playerInjuredHurledIntoPlayer": "%{player}在球员被砸倒后受伤。",
  "game.log.playerInjuredMinion": "在队友%{teammate}使用“嗜血”能力后，%{player} 因此受伤。",
  "game.log.playerInjuredPitchInvasion": "%{player}在球场入侵期间受伤。",
  "game.log.playerInjuredTrapdoor": "%{player}从活板门掉下来后受伤。",
  "game.log.playerInjuredTrapdoorMonster": "%{player}被活板门攻击后受伤。",
  "game.log.playerMovedFollowUp": "%{player}从%{source}沿%{direction}方向跟进到%{destination}。",
  "game.log.playerMovedMark": "%{player}执行一次%{action}行动，从%{source}沿%{direction}方向移动到%{destination}。",
  "game.log.playerMovedOutOfReserves": "%{player}在%{destination}上场。",
  "game.log.playerMovedRun": "%{player}从%{source}沿%{direction}方向奔跑到%{destination}。",
  "game.log.playerMovedShadow": "%{player}因'%{bonusPlay}'，从%{source}沿%{direction}方向移动到%{destination}。",
  "game.log.playerMovedShoved": "%{player}从%{source}沿%{direction}方向被推离到%{destination}。",
  "game.log.playerMovedSidestep": "%{player}从%{source}沿%{direction}方向侧步到%{destination}。",
  "game.log.playerMovedToReservesAfterTouchdown": "%{player}走到替补席。",
  "game.log.playerNumbersWereSetUp": "首发球员的号码已确定。",
  "game.log.playerPassedBall": "%{player} 把球从%{source}传到%{destination}。",
  "game.log.playerPickedUpLooseBall": "%{player}捡起地上的球。",
  "game.log.playerReplacedInReservesAfterTouchdown": "%{oldPlayer}被替换为%{newPlayer}。",
  "game.log.playerReset": "%{player}因“重置！”随机事件卡的效果而被移除出球场。",
  "game.log.playerScoredTouchdown": "%{player}达阵得分。",
  "game.log.playerSentOff": "%{player}被驱逐出场。",
  "game.log.playerStoodUp": "%{player}起身。",
  "game.log.playerThrewBomb": "%{player}把炸弹从%{source}投掷到%{destination}。",
  "game.log.rolledForArmour": "此次护甲检定为%{result}：%{coachName}的掷骰结果为：%{die}。",
  "game.log.rolledForBlock": "%{coachName} 的阻挡骰结果为%{results}。",
  "game.log.rolledForDirection": "%{coachName}的方向掷骰结果为：%{result}。",
  "game.log.rolledForFoul": "%{coachName}的犯规掷骰结果为：%{results}。",
  "game.log.rolledForHurlTeammate": "%{coachName}此次投掷队友的掷骰检定（传球检定）的掷%{die}骰结果为：%{result}。",
  "game.log.rolledForPass": "%{coachName}此次传球检定的掷%{die}骰结果为：%{result}。",
  "game.log.rolledForPitchInvasion": "%{coachName}的“球场入侵”随机事件卡掷骰结果为：%{result}。",
  "game.log.rolledForRunDistance": "%{coachName}的移动最大距离掷骰结果为：%{result}。",
  "game.log.rolledForTrapdoor": "%{coachName}的活板门随机结果:%{square}。",
  "game.log.scoreUpdated": "%{coachName}的得分从%{increment}增加到%{total}。",
  "game.log.selectedBlockResult": "%{coachName}选择的阻挡结果为：%{result}。",
  "game.log.selectedBoard": "%{coachName}选择的球场为：%{board}。",
  "game.log.selectedChallengeDeckConfig": "%{coachName}选择的挑战卡卡组为：%{deckConfig}。",
  "game.log.selectedLooseBallDirection": "%{player}选择的掉球落点为%{direction}。",
  "game.log.selectedNoRookieBonus": "%{coachName}选择没有“值得关注的新秀”卡。",
  "game.log.selectedOpponentRookieBonus": "%{coachName}选择让对方教练获得“值得关注的新秀”卡。",
  "game.log.selectedRuleset": "%{coachName}选择的规则版本为：%{ruleset}。",
  "game.log.selectedSelfRookieBonus": "%{coachName}选择自己获得“值得关注的新秀”卡。",
  "game.log.selectedTeam": "%{coachName}选择的球队为：%{team}。",
  "game.log.startingDeckWasSetUp": "挑战卡卡组已初始化，有%{count}张卡。",
  "game.log.startingHandWasSetUp": "%{coachName}部署其自己的球员。",
  "game.log.startingPlayersWereSetUp": "%{coachName}的球员已部署完毕。",
  "game.log.trapdoorClosed": "位于%{square}的活板门已关闭。",
  "game.log.trapdoorOpened": "位于%{square}的活板门已开启。",
  "game.log.usedOffensiveSpecialist": "%{player}使用其'%{skill}'能力来重掷。",
  "game.ordinal.0": "1号",
  "game.ordinal.1": "2号",
  "game.ordinal.2": "3号",
  "game.passRollModification.longDistance": "长距离",
  "game.passRollModification.obstructed": "活跃挑战卡区",
  "game.passRollModification.targetMarked": "目标球员被盯防",
  "game.playerIndicator.blackOrcBlackOrc": "BO",
  "game.playerIndicator.blackOrcGoblinBruiser": "GB",
  "game.playerIndicator.blitzer": "BZ",
  "game.playerIndicator.blocker": "BK",
  "game.playerIndicator.catcher": "C",
  "game.playerIndicator.chaosBeastman": "BM",
  "game.playerIndicator.chaosChosenBlocker": "CB",
  "game.playerIndicator.darkElfWitchElf": "WE",
  "game.playerIndicator.dwarfTrollslayer": "TS",
  "game.playerIndicator.gnomeBeastmaster": "BM",
  "game.playerIndicator.gnomeIllusionist": "IL",
  "game.playerIndicator.gnomeTreeman": "TM",
  "game.playerIndicator.gnomeWoodlandFox": "WF",
  "game.playerIndicator.goblinGoblin": "G",
  "game.playerIndicator.goblinTroll": "T",
  "game.playerIndicator.halflingHefty": "HE",
  "game.playerIndicator.halflingTreeman": "TM",
  "game.playerIndicator.khorneBloodseeker": "BS",
  "game.playerIndicator.khorneKhornegor": "KH",
  "game.playerIndicator.khorneMarauder": "MA",
  "game.playerIndicator.lineman": "L",
  "game.playerIndicator.lizardmenChameleonSkinkCatcher": "CS",
  "game.playerIndicator.lizardmenSaurusBlocker": "SB",
  "game.playerIndicator.lizardmenSkinkRunner": "SR",
  "game.playerIndicator.necromanticFleshGolem": "FG",
  "game.playerIndicator.necromanticGhoul": "G",
  "game.playerIndicator.necromanticWerewolf": "WE",
  "game.playerIndicator.necromanticWraith": "WR",
  "game.playerIndicator.necromanticZombie": "Z",
  "game.playerIndicator.nobleGuard": "BG",
  "game.playerIndicator.norseBearBoar": "BB",
  "game.playerIndicator.norseBerserker": "BE",
  "game.playerIndicator.norseUlfwerener": "U",
  "game.playerIndicator.norseValkyrie": "V",
  "game.playerIndicator.nurgleBloater": "B",
  "game.playerIndicator.nurglePestigor": "P",
  "game.playerIndicator.ogreGnoblar": "G",
  "game.playerIndicator.ogreOgre": "O",
  "game.playerIndicator.runner": "R",
  "game.playerIndicator.skavenGutterRunner": "GR",
  "game.playerIndicator.snotlingFungusFlinga": "FF",
  "game.playerIndicator.snotlingFunHoppa": "FH",
  "game.playerIndicator.snotlingPumpWagon": "PW",
  "game.playerIndicator.snotlingSnotling": "S",
  "game.playerIndicator.snotlingStiltyRunna": "SR",
  "game.playerIndicator.thrower": "T",
  "game.playerIndicator.undeadGhoul": "G",
  "game.playerIndicator.undeadMummy": "M",
  "game.playerIndicator.undeadSkeleton": "S",
  "game.playerIndicator.undeadWight": "W",
  "game.playerIndicator.undeadZombie": "Z",
  "game.playerIndicator.vampireBlitzer": "VB",
  "game.playerIndicator.vampirePasser": "VT",
  "game.playerIndicator.vampireRunner": "VR",
  "game.playerIndicator.vampireThrall": "TH",
  "game.playerIndicator.woodElfWardancer": "WD",
  "game.playerName.amazonBlitzer": "亚马逊队 · 食人鱼勇士突袭手",
  "game.playerName.amazonBlocker": "亚马逊队 · 豹勇士阻挡者",
  "game.playerName.amazonLinewoman": "亚马逊队 · 鹰勇士线锋",
  "game.playerName.amazonThrower": "亚马逊队 · 狂蟒传球手",
  "game.playerName.blackOrcBlackOrc": "黑兽人队 · 黑兽人",
  "game.playerName.blackOrcGoblin": "黑兽人队 · 哥布林",
  "game.playerName.chaosBeastman": "混沌神选队 · 野兽人",
  "game.playerName.chaosChosenBlocker": "混沌神选队 · 混沌阻挡者",
  "game.playerName.darkElfBlitzer": "黑暗精灵队 · 突袭手",
  "game.playerName.darkElfLineman": "黑暗精灵队 · 线锋",
  "game.playerName.darkElfRunner": "黑暗精灵队 · 跑卫",
  "game.playerName.darkElfWitchElf": "黑暗精灵队 · 巫灵",
  "game.playerName.dwarfBlitzer": "矮人队 · 突袭手",
  "game.playerName.dwarfLineman": "矮人队 · 线锋",
  "game.playerName.dwarfRunner": "矮人队 · 跑卫",
  "game.playerName.dwarfTrollslayer": "矮人队 · 巨魔屠夫",
  "game.playerName.elfBlitzer": "精灵联合队 · 突袭手",
  "game.playerName.elfCatcher": "精灵联合队 · 接球手",
  "game.playerName.elfLineman": "精灵联合队 · 线锋",
  "game.playerName.elfPasser": "精灵联合队 · 传球手",
  "game.playerName.gnomeBeastmaster": "侏儒队 · 驯兽师",
  "game.playerName.gnomeIllusionist": "侏儒队 · 幻术家",
  "game.playerName.gnomeLineman": "侏儒队 · 线锋",
  "game.playerName.gnomeTreeman": "侏儒队 · 树人",
  "game.playerName.gnomeWoodlandFox": "侏儒队 · 林地狐狸",
  "game.playerName.goblinGoblin": "哥布林队 · 哥布林",
  "game.playerName.goblinTroll": "哥布林队 · 巨魔",
  "game.playerName.halflingCatcher": "半身人队 · 接球手",
  "game.playerName.halflingHefty": "半身人队 · 壮汉",
  "game.playerName.halflingHopeful3E": "半身人队 · 希望之星",
  "game.playerName.halflingHopeful4E": "半身人队 · 线锋",
  "game.playerName.halflingTreeman": "半身人队 · 树人",
  "game.playerName.humanBlitzer": "人类队 · 突袭手",
  "game.playerName.humanCatcher": "人类队 · 接球手",
  "game.playerName.humanLineman": "人类队 · 线锋",
  "game.playerName.humanPasser": "人类队 · 传球手",
  "game.playerName.khorneBloodseeker": "恐虐队 · 寻血者",
  "game.playerName.khorneKhorngor": "恐虐队 · 恐角兽",
  "game.playerName.khorneMarauder": "恐虐队 · 血裔掠夺者",
  "game.playerName.lizardmenChameleonSkinkCatcher": "蜥蜴人队 · 变色龙",
  "game.playerName.lizardmenSaurusBlocker": "蜥蜴人队 · 梭蜥阻挡者",
  "game.playerName.lizardmenSkinkRunner": "蜥蜴人队 · 灵蜥",
  "game.playerName.necromanticFleshGolem": "死灵法术队 · 血肉魔像",
  "game.playerName.necromanticGhoul": "死灵法术队 · 食尸鬼",
  "game.playerName.necromanticWerewolf": "死灵法术队 · 狼人",
  "game.playerName.necromanticWraith": "死灵法术队 · 幽魂",
  "game.playerName.necromanticZombie": "死灵法术队 · 僵尸",
  "game.playerName.nobleBlitzer": "帝国贵族队 · 突袭手",
  "game.playerName.nobleGuard3E": "帝国贵族队 · 守卫",
  "game.playerName.nobleGuard4E": "帝国贵族队 · 守卫",
  "game.playerName.nobleLineman": "帝国贵族队 · 线锋",
  "game.playerName.noblePasser": "帝国贵族队 · 传球手",
  "game.playerName.norseBeerBoar": "诺斯队 · 啤酒猪",
  "game.playerName.norseBerserker": "诺斯队 · 狂战士",
  "game.playerName.norseLineman": "诺斯队 · 线锋",
  "game.playerName.norseUlfwerener": "诺斯队 · 狼战士",
  "game.playerName.norseValkyrie": "诺斯队 · 女武神",
  "game.playerName.nurgleBloater": "纳垢队 · 肿胀者",
  "game.playerName.nurgleLineman": "纳垢队 · 线锋",
  "game.playerName.nurglePestigor": "纳垢队 · 疫角兽",
  "game.playerName.ogreGnoblar": "食人魔队 · 孬不拉",
  "game.playerName.ogreOgre": "食人魔队 · 食人魔",
  "game.playerName.orcBigUnBlocker": "兽人队 · 大块头阻挡者",
  "game.playerName.orcBlitzer": "兽人队 · 突袭手",
  "game.playerName.orcLineman": "兽人队 · 线锋",
  "game.playerName.orcPasser": "兽人队 · 传球手",
  "game.playerName.skavenBlitzer": "斯卡文鼠人队 · 突袭手",
  "game.playerName.skavenGutterRunner": "斯卡文鼠人队 · 下水沟跑卫",
  "game.playerName.skavenLineman": "斯卡文鼠人队 · 线锋",
  "game.playerName.skavenPasser": "斯卡文鼠人队 · 传球手",
  "game.playerName.snotlingFungusFlinga": "鼻涕精队 · 霉菌散布者",
  "game.playerName.snotlingFunHoppa": "鼻涕精队 · 欢乐跳跳",
  "game.playerName.snotlingPumpWagon": "鼻涕精队 · 泵车",
  "game.playerName.snotlingSnotling": "鼻涕精队 · 鼻涕精",
  "game.playerName.snotlingStiltyRunna": "鼻涕精队 · 高跷跑卫",
  "game.playerName.undeadGhoul": "蹒跚不死者队 · 食尸鬼",
  "game.playerName.undeadMummy": "蹒跚不死者队 · 木乃伊",
  "game.playerName.undeadSkeleton": "蹒跚不死者队 · 骷髅",
  "game.playerName.undeadWight": "蹒跚不死者队 · 尸妖",
  "game.playerName.undeadZombie": "蹒跚不死者队 · 僵尸",
  "game.playerName.vampireBlitzer": "吸血鬼队 · 突袭手",
  "game.playerName.vampirePasser": "吸血鬼队 · 传球手",
  "game.playerName.vampireRunner": "吸血鬼队 · 跑卫",
  "game.playerName.vampireThrall": "吸血鬼队 · 奴仆",
  "game.playerName.woodElfCatcher": "木精灵队 · 接球手",
  "game.playerName.woodElfLineman": "木精灵队 · 线锋",
  "game.playerName.woodElfPasser": "木精灵队 · 传球手",
  "game.playerName.woodElfWardancer": "木精灵队 · 战舞者",
  "game.prompt.arrangePlayers": "将你的球员部署到你的端区",
  "game.prompt.buttonCancel": "取消",
  "game.prompt.buttonConfirm": "确认",
  "game.prompt.buttonContinue": "继续",
  "game.prompt.buttonDecline": "不使用",
  "game.prompt.buttonNo": "否",
  "game.prompt.buttonReroll": "重掷",
  "game.prompt.buttonReset": "重设",
  "game.prompt.buttonUse": "使用",
  "game.prompt.buttonYes": "是",
  "game.prompt.claimObjectives1": "获得%{ordinal0}挑战卡？",
  "game.prompt.claimObjectives2": "获得%{ordinal0}或%{ordinal1}挑战卡？",
  "game.prompt.claimObjectives3": "获得%{ordinal0}, %{ordinal1},或%{ordinal2}挑战卡？",
  "game.prompt.configureChallengeDeck": "配置挑战卡卡组",
  "game.prompt.configureChallengeDeckLong3E": "包含残局挑战卡？",
  "game.prompt.configureChallengeDeckLong4E": "包含随机事件卡？",
  "game.prompt.configureChallengeDeckRandom": "每张挑战卡背面的附赠战术是否随机？",
  "game.prompt.confirmForfeitGame": "真的弃赛？",
  "game.prompt.declareActionMore": "选择一名球员并分配行动。你还剩余%{count} 个球员行动可供分配。",
  "game.prompt.declareActionOne": "选择一名球员并分配行动。你还剩余1个球员行动可供分配。",
  "game.prompt.followUp": "是否跟进？",
  "game.prompt.randomSelectionGuidance": "或者随机选择球场？",
  "game.prompt.selectBlockResult": "选择一个阻挡结果。",
  "game.prompt.selectBlockResultOrUseBonusPlay": "选择一个阻挡结果，或者发动'%{bonusPlay}'附赠战术。",
  "game.prompt.selectBlockResultOrUseSkill": "选择一个阻挡结果，或者使用'%{skill}'能力。",
  "game.prompt.selectBoard": "选择一个球场",
  "game.prompt.selectCardsToDiscard": "从你的手卡中选择一张挑战卡丢弃。",
  "game.prompt.selectEmergencyReserves": "由于“紧急上场”，请选择你的一名球员。",
  "game.prompt.selectForBonusPlay": "由于'%{bonusPlay}'附赠战术，请选择你的一名球员，或选择不发动。",
  "game.prompt.selectForSkill": "由于'%{skill}'能力，请选择你的一名球员，或选择不使用。",
  "game.prompt.selectLooseBallDirection": "请选择球的掉落方向。",
  "game.prompt.selectObjectiveToDiscard": "请选择丢弃一张流动挑战卡。",
  "game.prompt.selectRookieBonusRecipient": "选择谁获得“值得关注的新秀”卡",
  "game.prompt.selectRuleset": "选择规则版本",
  "game.prompt.selectSquare": "由于%{action}行动，请选择一个方格。",
  "game.prompt.selectSquares": "由于%{action}行动，请选择方格。",
  "game.prompt.selectTarget": "由于%{action}行动，请选择目标。",
  "game.prompt.selectTeam": "选择你的球队",
  "game.prompt.selectTeammate": "由于%{action}行动，请选择一名队友。",
  "game.prompt.selectTeamMouseoverGuidance": "将鼠标悬停在每名球员上以检查它们的详细信息。",
  "game.prompt.useBananaSkinMore": "由于“香蕉皮”，请选择一名球员，或选择不发动。",
  "game.prompt.useBananaSkinOne": "发动香蕉皮？",
  "game.prompt.useBlockResultOrUseBonusPlay": "选择这个阻挡结果，或发动'%{bonusPlay}'附赠战术。",
  "game.prompt.useBlockResultOrUseSkill": "选择这个阻挡结果，或使用'%{skill}'能力。",
  "game.prompt.useBonusPlay": "发动'%{bonusPlay}'附赠战术？",
  "game.prompt.useFreeActionMore": "由于额外的%{action}行动，请选择一名球员，或选择不执行。",
  "game.prompt.useFreeActionOne": "执行一次额外的%{action}行动？",
  "game.prompt.useSkill": "使用'%{skill}'能力？",
  "game.rookieBonusRecipient.none": "无人获得",
  "game.rookieBonusRecipient.opponent": "把此卡给你的对手",
  "game.rookieBonusRecipient.self": "自己获得此卡",
  "game.ruleset.fourthEdition": "终极版Ⅱ（ultimate second edition）",
  "game.ruleset.fourthEditionCrushCustom": "终极版Ⅱ(“Crush”discord社区第三方变体规则)",
  "game.ruleset.thirdEdition": "终极版（ultimate edition）",
  "game.skillDescription.bloodlust": "在该球员执行完阻挡行动、并结算完随后的“获得挑战卡步骤”后，如果此次阻挡行动的阻挡结果出现“失误”，该球员受伤。如果该球员拿住球，则球弹跳。",
  "game.skillDescription.bomber": "该球员可以在无人盯防状态下执行阻挡行动。在它周围3格范围内选择一名无人盯防或被盯防的对方球员作为阻挡目标。这种阻挡行动不能获得协助，并把阻挡结果的“推离”视为“失误”。",
  "game.skillDescription.catchersInstincts": "如果该球员处于无人盯防状态、并且是一次成功的传球行动的目标球员（不是手递手传球），它可以执行一次额外的奔跑行动。",
  "game.skillDescription.claws": "当该球员执行一次阻挡行动时，掷阻挡骰和一枚D6。如果这枚D6的结果为6，阻挡目标会直接受伤--不要结算此次阻挡结果。",
  "game.skillDescription.defensive": "与该球员相邻的对方球员不能协助阻挡。",
  "game.skillDescription.dumpOff": "当该球员被选为阻挡行动的目标时，它可以中断此次行动并执行一次无修正的、额外的短距离传球（行动）（或手递手传球），即使它处于被盯防状态。",
  "game.skillDescription.elusive": "当该球员执行一次奔跑行动时，它可以移动到与对方球员相邻的方格，但在执行完此次奔跑行动后，它必须处于无人盯防状态。",
  "game.skillDescription.enforcer": "当该球员执行一次阻挡行动时，你必须结算此次掷骰的所有阻挡结果、并确定好它们的结算顺序。对于每个含有“阻挡目标被击倒”的阻挡结果，对方教练必须为阻挡目标做护甲检定。在结算完一个阻挡结果后，该球员必须跟进。",
  "game.skillDescription.ethereal": "当该球员执行一次奔跑行动时，它可以移动到与对方球员相邻的方格，并穿过障碍物、我方球员和对方球员，但在执行完此次奔跑行动后，它必须处于无人盯防状态且不在被一名球员或障碍物占据的方格。",
  "game.skillDescription.expertPasser": "每当该球员的传球检定结果为失败，它可以重掷此次掷骰。",
  "game.skillDescription.frenzied": "在该球员执行完一次盯防行动后，它可以对其当前正在盯防的球员执行一次额外的阻挡行动。",
  "game.skillDescription.handlingSkills": "每当该球员以任何方式移动到一个被球占据的方格时，它就会把那个球捡起来，如同它执行奔跑行动那样。",
  "game.skillDescription.headbutt": "如果该球员执行了一次奔跑行动，紧接着执行了一次盯防行动，它可以立即执行一次额外的阻挡行动。",
  "game.skillDescription.hitAndRun": "在该球员执行完一次阻挡行动后，它可以执行一次额外的奔跑行动。此次额外的奔跑行动，在它与对方球员相邻的情况下也能执行。",
  "game.skillDescription.hulkingBrute": "当该球员执行一次阻挡行动时，把阻挡结果的“擒抱”和“猛撞！”视为“超级猛撞！”。此外，如果该球员被选为阻挡行动的阻挡目标，把阻挡结果的“推离”视为“失误”。",
  "game.skillDescription.hurlTeammate": "该球员可以执行投掷队友行动。",
  "game.skillDescription.insignificant": "对方球员在执行奔跑行动期间可以移动到与该球员相邻的方格。此外，当该球员执行一次阻挡行动时，把阻挡结果的“擒抱”视为“失误”。",
  "game.skillDescription.leap": "当该球员执行一次奔跑行动时，它可以移动到与对方球员相邻的方格并穿过我方球员和对方球员，但在执行完此次奔跑行动后，它必须处于无人盯防状态，而不是被盯防状态。",
  "game.skillDescription.litheCreature": "当该球员执行一次奔跑行动时，它可以移动到与对方球员相邻的方格，但在执行完此次奔跑行动后，它必须处于无人盯防状态。此外，该球员不能执行传球行动（包括手递手传球）。",
  "game.skillDescription.mightyBlow": "当该球员执行一次阻挡行动时，把阻挡结果的“猛撞！”视为“超级猛撞！”。",
  "game.skillDescription.minion": "当一名与该球员相邻的队友因其“嗜血”能力而受伤时，作为替代，你可以让该球员受伤。",
  "game.skillDescription.offensiveSpecialist": "当该球员执行一次阻挡行动时，你可以选择重掷此次阻挡骰。",
  "game.skillDescription.pickMeUp": "在该球员执行完任何行动时，与它相邻的任何倒地球员都可以执行一次额外的起身行动。",
  "game.skillDescription.regenerate": "在“回合前流程”后，但在你执行第一次球员行动前，如果该球员处于倒地状态，它可以立即执行一次额外的起身行动。",
  "game.skillDescription.runningPass": "在该球员执行完奔跑行动后，它可以执行一次额外的短距离传球（行动）。",
  "game.skillDescription.rush": "当该球员执行一次奔跑行动时，它可以移动到与对方球员相邻的方格，但这样做会结束此次行动。",
  "game.skillDescription.safeHands": "如果该球员在拿住球的情况下被击倒，你可以选择球弹跳到与其相邻的任何一个方格，而不是掷一枚D8。",
  "game.skillDescription.standFirm": "当该球员被选为阻挡行动的目标时，把阻挡结果的“推离”视为“失误”。",
  "game.skillDescription.titchy": "对方球员在执行奔跑行动期间可以移动到与该球员相邻的方格，但这样做会结束此次行动。当该球员执行一次阻挡行动时，把阻挡结果的“擒抱”视为“失误”。",
  "game.skillDescription.violent": "当该球员执行一次阻挡行动或犯规行动时，掷阻挡骰和一枚D6。如果这枚D6的结果为6，目标会直接受伤--不要结算此次阻挡骰的结果。",
  "game.skillDescription.wardance": "该球员可以执行一次额外的侧步行动。",
  "game.skillDescription.warMachine": "该球员可以在被盯防的情况下执行奔跑行动。当该球员执行一次奔跑行动时，它可以移动到与对方球员相邻的方格、并在执行完此次奔跑行动后处于无人盯防状态或被盯防状态。该球员的阻挡行动不能获得协助。",
  "game.skillDescription.woodlandAid": "假如该球员被选为阻挡行动的目标，此次阻挡行动不能获得协助。",
  "game.skillName.bloodlust": "嗜血",
  "game.skillName.bomber": "投弹手",
  "game.skillName.catchersInstincts": "接球手本能",
  "game.skillName.claws": "爪子",
  "game.skillName.defensive": "防守",
  "game.skillName.dumpOff": "抛球",
  "game.skillName.elusive": "难以捕捉",
  "game.skillName.enforcer": "执行者",
  "game.skillName.ethereal": "虚无",
  "game.skillName.expertPasser": "传球专家",
  "game.skillName.frenzied": "狂暴",
  "game.skillName.handlingSkills": "灵活捡球",
  "game.skillName.headbutt": "头槌",
  "game.skillName.hitAndRun": "打完就跑",
  "game.skillName.hulkingBrute": "笨重野兽",
  "game.skillName.hurlTeammate": "投掷队友",
  "game.skillName.insignificant": "无足轻重",
  "game.skillName.leap": "飞腾跳跃",
  "game.skillName.litheCreature": "轻盈生物",
  "game.skillName.mightyBlow": "猛力一击",
  "game.skillName.minion": "仆从",
  "game.skillName.offensiveSpecialist": "进攻专家",
  "game.skillName.pickMeUp": "提神啤酒",
  "game.skillName.regenerate": "再生",
  "game.skillName.runningPass": "跑传",
  "game.skillName.rush": "猛冲",
  "game.skillName.safeHands": "安全掉球",
  "game.skillName.standFirm": "巍然不动",
  "game.skillName.titchy": "渺小",
  "game.skillName.violent": "暴力",
  "game.skillName.wardance": "战舞",
  "game.skillName.warMachine": "战争机器",
  "game.skillName.woodlandAid": "林地支援",
  "game.team.amazon": "亚马逊",
  "game.team.blackOrc": "黑兽人",
  "game.team.chaos3E": "混沌",
  "game.team.chaos4E": "混沌神选",
  "game.team.darkElf": "黑暗精灵",
  "game.team.dwarf": "矮人",
  "game.team.elf3E": "精灵",
  "game.team.elf4E": "精灵联合",
  "game.team.gnome": "侏儒",
  "game.team.goblin": "哥布林",
  "game.team.halfling": "半身人",
  "game.team.human": "人类",
  "game.team.khorne": "恐虐",
  "game.team.lizardmen": "蜥蜴人",
  "game.team.necromantic": "死灵法术",
  "game.team.noble3E": "贵族",
  "game.team.noble4E": "帝国贵族",
  "game.team.norse": "诺斯",
  "game.team.nurgle": "纳垢",
  "game.team.ogre": "食人魔",
  "game.team.orc": "兽人",
  "game.team.skaven": "斯卡文鼠人",
  "game.team.snotling": "鼻涕精",
  "game.team.undead3E": "不死",
  "game.team.undead4E": "蹒跚不死者",
  "game.team.vampire": "吸血鬼",
  "game.team.woodElf": "木精灵",
  "game.ui.cardLabelDeck": "挑战卡卡组",
  "game.ui.cardLabelDiscard": "弃牌区",
  "game.ui.cardLabelFirst": "1号",
  "game.ui.cardLabelSecond": "2号",
  "game.ui.cardLabelThird": "3号",
  "game.ui.copyLog": "复制日志",
  "game.ui.emergencyReserves": "紧急上场值:%{count}",
  "game.ui.forfeitGame": "放弃比赛",
  "game.ui.playerIndicatorsHidden": "隐藏",
  "game.ui.playerIndicatorsLabel": "球员显示",
  "game.ui.playerIndicatorsNumbers": "号码",
  "game.ui.playerIndicatorsPositions": "位置",
  "game.ui.playerNumber": "#%{number}",
  "game.ui.promptGameIsFinished": "比赛已结束",
  "game.ui.promptUpdating": "更新",
  "game.ui.promptWaitingForCoach": "等待%{coachName}",
  "game.ui.promptWaitingForServer": "等待服务器",
  "game.ui.replayHeader": "回放",
  "game.ui.replayPause": "暂停",
  "game.ui.replayPlay": "播放",
  "game.ui.replayStepBack": "-",
  "game.ui.replayStepForward": "+",
  "game.ui.spriteThemeLabel": "棋子图片样式",
  "game.ui.statArmour": "护甲值",
  "game.ui.statBlock": "阻挡值",
  "game.ui.statMove": "移动值",
  "game.ui.statPass": "传球值",
  "game.ui.throwRulerHide": "隐藏",
  "game.ui.throwRulerLabel": "传球尺",
  "game.ui.throwRulerShow": "显示",
  "game.ui.versusAbbreviation": "vs",
  "index.firstParagraph": "欢迎来到%{avalonFootballName},这个是%{blitzBowlName}（此桌游本体由%{gamesWorkshopName}制作）的线上桌游对决系统，免费。",
  "index.secondParagraph": "注册或登录以开始游戏。",
  "lobby.coaches.guidance": "这是当前大厅里其他教练的名单。需要有其他教练在此才能开始新比赛。",
  "lobby.coaches.header": "教练",
  "lobby.coaches.table.showAll": "显示所有教练",
  "lobby.coaches.table.status.accept": "接受",
  "lobby.coaches.table.status.decline": "拒绝",
  "lobby.coaches.table.status.gameInProgress": "比赛正在进行中",
  "lobby.coaches.table.status.header": "状态",
  "lobby.coaches.table.status.invite": "邀请",
  "lobby.coaches.table.username.header": "用户名",
  "lobby.games.guidance": "这是一份比赛列表。你可以观看其他教练的比赛或重新加入自己的比赛。你可以观看已完成比赛的回放。",
  "lobby.games.header": "比赛",
  "lobby.games.table.details.header": "详情",
  "lobby.games.table.lastActive.finished": "结束于%{date}",
  "lobby.games.table.lastActive.header": "上次激活时间",
  "lobby.games.table.showAll": "显示所有比赛",
  "lobby.games.table.status.header": "状态",
  "lobby.games.table.status.rejoin": "再次加入",
  "lobby.games.table.status.spectate": "观战",
  "lobby.games.table.status.watchReplay": "查看回放",
  "login.error": "用户名或密码无效。",
  "login.submit": "登录",
  "page.credits": "代码和像素化由%{ibsh}负责。角色设计由%{daveYourFave}负责。%{portOBowlName} 模型由%{portOBowlAttribution}负责。",
  "page.footer": "%{blitzBowlLink}及其相关术语归%{gamesWorkshopLink}所有，未经许可不得使用。本网站不属于官方网站，与%{gamesWorkshopName}无关，也不对其地位构成挑战。你必须拥有%{blitzBowlName}的实体桌游才能知道如何玩%{avalonFootballName}。",
  "page.title.help": "如何玩",
  "page.title.lobby": "大厅",
  "page.title.login": "登录",
  "page.title.register": "注册",
  "page.topbar.loggedIn": "%{username}已登录",
  "page.topbar.logout": "登出",
  "page.topbar.returnToLobby": "返回大厅",
  "register.confirmPassword": "确认密码",
  "register.error.passwordForm": "密码必须为8至64个字符，且至少包含一个大写字母、一个小写字母、一个数字和一个特殊符号（例如：！@#$&*）。",
  "register.error.passwordMatch": "密码不符合要求",
  "register.error.usernameForm": "用户名必须为4到12个字符，且只能包含ASCII字符，不能包含空格。",
  "register.error.usernameTaken": "该用户名已被注册",
  "register.errorHeader": "请修复以下错误：",
  "register.submit": "注册",
  "socket.connected": "已连接",
  "socket.connecting": "连接中",
  "socket.stopped": "已停止",
  "socket.waiting": "请稍后",
  "user.password": "密码",
  "user.username": "用户名"
}
